calcrule_validations/__init__.py
calcrule_validations/admin.py
calcrule_validations/apps.py
calcrule_validations/calculation_rule.py
calcrule_validations/config.py
calcrule_validations/models.py
calcrule_validations/tests.py
calcrule_validations/urls.py
calcrule_validations/views.py
calcrule_validations/migrations/__init__.py
calcrule_validations/strategies/__init__.py
calcrule_validations/strategies/base_strategy.py
calcrule_validations/strategies/deduplication_individual_validation_strategy.py
calcrule_validations/strategies/deduplication_validation_strategy.py
calcrule_validations/strategies/email_validation_strategy.py
calcrule_validations/strategies/number_input_validation_strategy.py
calcrule_validations/strategies/phone_number_validation_strategy.py
calcrule_validations/strategies/validation_strategy_interface.py
calcrule_validations/strategies/validation_strategy_storage.py
openimis_be_calcrule_validations-1.2.0.dist-info/licenses/LICENSE.md
openimis_be_calcrule_validations-1.2.0.dist-info/METADATA
openimis_be_calcrule_validations-1.2.0.dist-info/WHEEL
openimis_be_calcrule_validations-1.2.0.dist-info/top_level.txt
openimis_be_calcrule_validations-1.2.0.dist-info/RECORD
